citycom_mv_api/__init__.py
citycom_mv_api/citycom_mv_client.py
citycom_mv_api/commons.py
citycom_mv_api/const.py
citycom_mv_api/data.py
citycom_mv_api/login.py
citycom_mv_api/models/Address.py
citycom_mv_api/models/Bucket.py
citycom_mv_api/models/ConsumptionHistoryData.py
citycom_mv_api/models/ConsumptionTimeSeries.py
citycom_mv_api/models/CustomerInformation.py
citycom_mv_api/models/Location.py
citycom_mv_api/models/Meter.py
citycom_mv_api/models/MeterProperty.py
citycom_mv_api/models/MetersInfo.py
citycom_mv_api/models/Property.py
citycom_mv_api/models/Reading.py
citycom_mv_api/models/TimePeriodOptions.py
citycom_mv_api/models/User.py
citycom_mv_api/models/auth_error.py
citycom_mv_api/models/exceptions.py
citycom_mv_api/models/jwt.py
citycom_mv_api-1.0.1.dist-info/LICENSE
citycom_mv_api-1.0.1.dist-info/METADATA
citycom_mv_api-1.0.1.dist-info/WHEEL
citycom_mv_api-1.0.1.dist-info/RECORD
