Metadata-Version: 2.1
Name: citycom-mv-api
Version: 1.0.1
Summary: A Python wrapper for citycom-mv water meters api
Home-page: https://github.com/Shenharo/py-citycom-mv-api
License: MIT
Keywords: python,poetry,api,citcom,citcom-mv,israel,water,meter
Author: shenharo
Maintainer: Omer Shenhar
Maintainer-email: shenharo@gmail.com
Requires-Python: >=3.11
Classifier: License :: OSI Approved :: MIT License
Classifier: Programming Language :: Python :: 3
Classifier: Programming Language :: Python :: 3.11
Classifier: Programming Language :: Python :: 3.12
Requires-Dist: aiofiles (>=23.2.1,<24.0.0)
Requires-Dist: aiohttp (>=3.9.1,<4.0.0)
Requires-Dist: cachetools (>=5.3.3,<6.0.0)
Requires-Dist: loguru (>=0.7.2,<0.8.0)
Requires-Dist: mashumaro (>=3.12,<4.0)
Requires-Dist: pkce (>=1.0.3,<2.0.0)
Requires-Dist: pytz (>=2024.1,<2025.0)
Requires-Dist: requests (>=2.31.0,<3.0.0)
Project-URL: Repository, https://github.com/Shenharo/py-citycom-mv-api
